cellstate_pred/__init__.py
cellstate_pred/_inference.py
cellstate_pred/feature_extraction.py
cellstate_pred/image_utils.py
cellstate_pred-0.1.0.dist-info/METADATA
cellstate_pred-0.1.0.dist-info/WHEEL
cellstate_pred-0.1.0.dist-info/entry_points.txt
cellstate_pred-0.1.0.dist-info/top_level.txt
cellstate_pred-0.1.0.dist-info/RECORD
