Metadata-Version: 2.4
Name: cellstate-pred
Version: 0.1.0
Summary: Predict cell state (hypusine marker) based on deep learning morphological features
Author-email: avillanueva <avillanueva@cemm.at>
License: License :: OSI Approved :: GNU General Public License v3 or later (GPLv3+)
Project-URL: homepage, https://github.com/rendeirolab/cellstate-pred
Project-URL: documentation, https://github.com/rendeirolab/cellstate-pred/blob/main/README.md
Project-URL: repository, https://github.com/rendeirolab/cellstate-pred
Keywords: computational biology,bioinformatics
Classifier: Programming Language :: Python :: 3 :: Only
Classifier: Programming Language :: Python :: 3.12
Classifier: Programming Language :: Python :: 3.13
Classifier: Development Status :: 3 - Alpha
Classifier: Typing :: Typed
Classifier: License :: OSI Approved :: GNU General Public License v3 or later (GPLv3+)
Classifier: Topic :: Scientific/Engineering :: Bio-Informatics
Requires-Python: >=3.10
Requires-Dist: anndata>=0.11.4
Requires-Dist: cloudpickle>=3.1.1
Requires-Dist: datasets>=4.1.1
Requires-Dist: fa2-modified>=0.3.10
Requires-Dist: fastcluster>=1.2.6
Requires-Dist: igraph>=0.11.9
Requires-Dist: imagecodecs>=2025.3.30
Requires-Dist: ipykernel>=6.30.1
Requires-Dist: jupyterlab>=4.4.7
Requires-Dist: leidenalg>=0.10.2
Requires-Dist: matplotlib>=3.10.3
Requires-Dist: networkx>=3.4.2
Requires-Dist: numpy>=1.26.4
Requires-Dist: pandas>=2.3.0
Requires-Dist: parmap>=1.7.0
Requires-Dist: pingouin>=0.5.5
Requires-Dist: pooch>=1.8.2
Requires-Dist: pyarrow>=20.0.0
Requires-Dist: pymde>=0.1.18
Requires-Dist: scanpy>=1.11.3
Requires-Dist: scikit-image>=0.25.2
Requires-Dist: scikit-learn>=1.7.0
Requires-Dist: scipy>=1.15.3
Requires-Dist: seaborn>=0.13.2
Requires-Dist: seaborn-extensions>=0.2.1
Requires-Dist: tifffile>=2025.5.10
Requires-Dist: tqdm>=4.67.1
Requires-Dist: transformers>=4.56.2
Requires-Dist: umap-learn>=0.5.9.post2
